pymaltego/__init__.py
pymaltego/constants.py
pymaltego/entities.py
pymaltego/exceptions.py
pymaltego/messages.py
pymaltego/transforms.py
pymaltego-1.2.0.dist-info/DESCRIPTION.rst
pymaltego-1.2.0.dist-info/METADATA
pymaltego-1.2.0.dist-info/RECORD
pymaltego-1.2.0.dist-info/WHEEL
pymaltego-1.2.0.dist-info/metadata.json
pymaltego-1.2.0.dist-info/top_level.txt
