Metadata-Version: 2.0
Name: pymaltego
Version: 1.2.0
Summary: Package for developing Maltego Transforms
Home-page: https://github.com/pyvim/pymaltego
Author: Vitalii Maslov
Author-email: me@pyvim.com
License: MIT
Download-URL: https://github.com/pyvim/pyvim/tarball/master
Keywords: Maltego,transforms
Platform: UNKNOWN
Classifier: Environment :: Web Environment
Classifier: Intended Audience :: Developers
Classifier: Programming Language :: Python
Requires-Dist: lxml
